[
{
"question": "대화를 읽고, 밑줄 친 house의 뜻으로 알맞은 것을 고르세요.\n\nMom: Look at our new <u>house</u>.\nChild: Wow! What a nice house!",
"options": [
"집",
"교실",
"침실",
"부엌"
],
"difficulty": "easy",
"reward": 50,
"time": 10,
"answerIndex": 0
},
{
"question": "다음 밑줄 친 bedroom의 뜻으로 알맞은 것을 고르세요.\n\nThis is my <u>bedroom</u>. There are two beds.",
"options": [
"욕실",
"거실",
"침실",
"부엌"
],
"difficulty": "easy",
"reward": 50,
"time": 10,
"answerIndex": 2
},
{
"question": "밑줄 친 bathroom의 뜻으로 알맞은 것을 고르세요.\n\nThis is the <u>bathroom</u>. There is a sink and a toilet.",
"options": [
"침실",
"거실",
"부엌",
"욕실"
],
"difficulty": "easy",
"reward": 50,
"time": 10,
"answerIndex": 3
},
{
"question": "밑줄 친 living room의 뜻으로 알맞은 것을 고르세요.\n\nThis is the <u>living room</u>. There is a sofa.",
"options": [
"교실",
"거실",
"부엌",
"욕실"
],
"difficulty": "easy",
"reward": 50,
"time": 10,
"answerIndex": 1
},
{
"question": "밑줄 친 kitchen의 뜻으로 알맞은 것을 고르세요.\n\nThis is the <u>kitchen</u>. There is a stove and a sink.",
"options": [
"거실",
"부엌",
"침실",
"욕실"
],
"difficulty": "easy",
"reward": 50,
"time": 10,
"answerIndex": 1
},
{
"question": "밑줄 친 classroom의 뜻으로 알맞은 것을 고르세요.\n\nWelcome to our <u>classroom</u>.",
"options": [
"집",
"거실",
"교실",
"부엌"
],
"difficulty": "easy",
"reward": 50,
"time": 10,
"answerIndex": 2
},
{
"question": "밑줄 친 bed의 뜻으로 알맞은 것을 고르세요.\n\nThere is a <u>bed</u> in the bedroom.",
"options": [
"책상",
"침대",
"소파",
"테이블"
],
"difficulty": "easy",
"reward": 50,
"time": 10,
"answerIndex": 1
},
{
"question": "밑줄 친 desk의 뜻으로 알맞은 것을 고르세요.\n\nThere is a <u>desk</u> in the classroom.",
"options": [
"침대",
"책상",
"소파",
"욕조"
],
"difficulty": "easy",
"reward": 50,
"time": 10,
"answerIndex": 1
},
{
"question": "밑줄 친 sofa의 뜻으로 알맞은 것을 고르세요.\n\nThere is a <u>sofa</u> in the living room.",
"options": [
"변기",
"책상",
"소파",
"싱크대"
],
"difficulty": "easy",
"reward": 50,
"time": 10,
"answerIndex": 2
},
{
"question": "밑줄 친 table의 뜻으로 알맞은 것을 고르세요.\n\nThere is a big <u>table</u> in the kitchen.",
"options": [
"의자",
"책상",
"테이블",
"사물함"
],
"difficulty": "easy",
"reward": 50,
"time": 10,
"answerIndex": 2
},
{
"question": "밑줄 친 toilet의 뜻으로 알맞은 것을 고르세요.\n\nThere is a <u>toilet</u> in the bathroom.",
"options": [
"변기",
"침대",
"소파",
"책상"
],
"difficulty": "easy",
"reward": 50,
"time": 10,
"answerIndex": 0
},
{
"question": "밑줄 친 bath의 뜻으로 알맞은 것을 고르세요.\n\nI take a <u>bath</u> in the bathroom.",
"options": [
"식사",
"목욕",
"숙제",
"게임"
],
"difficulty": "easy",
"reward": 50,
"time": 10,
"answerIndex": 1
},
{
"question": "밑줄 친 stove의 뜻으로 알맞은 것을 고르세요.\n\nThere is a <u>stove</u> in the kitchen.",
"options": [
"싱크대",
"가스레인지(요리하는 기구)",
"책상",
"사물함"
],
"difficulty": "medium",
"reward": 50,
"time": 10,
"answerIndex": 1
},
{
"question": "밑줄 친 sink의 뜻으로 알맞은 것을 고르세요.\n\nThere is a <u>sink</u> in the kitchen.",
"options": [
"변기",
"침대",
"세면대, 싱크대",
"소파"
],
"difficulty": "medium",
"reward": 50,
"time": 10,
"answerIndex": 2
},
{
"question": "밑줄 친 locker의 뜻으로 알맞은 것을 고르세요.\n\nThere is a <u>locker</u> in the classroom.",
"options": [
"사물함",
"책상",
"침대",
"욕조"
],
"difficulty": "medium",
"reward": 50,
"time": 10,
"answerIndex": 0
},
{
"question": "다음 설명에 알맞은 단어를 고르세요.\n\n"우리가 자는 방입니다."",
"options": [
"bedroom",
"bathroom",
"kitchen",
"classroom"
],
"difficulty": "easy",
"reward": 50,
"time": 10,
"answerIndex": 0
},
{
"question": "다음 설명에 알맞은 단어를 고르세요.\n\n"우리가 요리하는 방입니다."",
"options": [
"living room",
"kitchen",
"bedroom",
"classroom"
],
"difficulty": "easy",
"reward": 50,
"time": 10,
"answerIndex": 1
},
{
"question": "다음 설명에 알맞은 단어를 고르세요.\n\n"우리가 텔레비전을 보고 쉬는 방입니다."",
"options": [
"kitchen",
"bathroom",
"living room",
"bedroom"
],
"difficulty": "easy",
"reward": 50,
"time": 10,
"answerIndex": 2
},
{
"question": "다음 설명에 알맞은 단어를 고르세요.\n\n"우리가 공부하고 배우는 곳입니다."",
"options": [
"house",
"bedroom",
"classroom",
"kitchen"
],
"difficulty": "easy",
"reward": 50,
"time": 10,
"answerIndex": 2
},
{
"question": "빈칸에 알맞은 말을 고르세요.\n\nThis is the ______.\n(이곳은 욕실입니다.)",
"options": [
"bedroom",
"bathroom",
"living room",
"kitchen"
],
"difficulty": "easy",
"reward": 50,
"time": 10,
"answerIndex": 1
},
{
"question": "빈칸에 알맞은 말을 고르세요.\n\nThis is the .\n(이곳은 거실입니다.)",
"options": [
"bedroom",
"bathroom",
"living room",
"classroom"
],
"difficulty": "easy",
"reward": 50,
"time": 10,
"answerIndex": 2
},
{
"question": "빈칸에 알맞은 말을 고르세요.\n\n a nice house!\n(정말 멋진 집이야!)",
"options": [
"What",
"How",
"What a",
"So"
],
"difficulty": "medium",
"reward": 50,
"time": 10,
"answerIndex": 2
},
{
"question": "빈칸에 알맞은 말을 고르세요.\n\nThere is a ______ in the living room.\n(거실에는 소파가 한 개 있습니다.)",
"options": [
"bed",
"locker",
"sofa",
"desk"
],
"difficulty": "easy",
"reward": 50,
"time": 10,
"answerIndex": 2
},
{
"question": "빈칸에 알맞은 말을 고르세요.\n\nThere are two ______ in the bedroom.\n(침실에는 침대가 두 개 있습니다.)",
"options": [
"bed",
"beds",
"sofa",
"tables"
],
"difficulty": "medium",
"reward": 50,
"time": 10,
"answerIndex": 1
},
{
"question": "빈칸에 알맞은 말을 고르세요.\n\nThere is a TV ______ the wall.\n(벽에 텔레비전이 하나 있습니다.)",
"options": [
"in",
"on",
"under",
"behind"
],
"difficulty": "medium",
"reward": 50,
"time": 10,
"answerIndex": 1
},
{
"question": "우리말과 뜻이 같은 영어 문장을 고르세요.\n\n"이곳은 욕실입니다."",
"options": [
"This is the bedroom.",
"This is the bathroom.",
"This is the living room.",
"This is the kitchen."
],
"difficulty": "medium",
"reward": 50,
"time": 10,
"answerIndex": 1
},
{
"question": "우리말과 뜻이 같은 영어 문장을 고르세요.\n\n"이곳은 거실입니다."",
"options": [
"This is the living room.",
"This is the bedroom.",
"This is the bathroom.",
"This is the classroom."
],
"difficulty": "medium",
"reward": 50,
"time": 10,
"answerIndex": 0
},
{
"question": "우리말과 뜻이 같은 영어 문장을 고르세요.\n\n"거실에는 소파가 한 개 있습니다."",
"options": [
"There are sofas in the living room.",
"There is a sofa in the living room.",
"There is a sofa in the bedroom.",
"There are two sofas in the living room."
],
"difficulty": "hard",
"reward": 50,
"time": 10,
"answerIndex": 1
},
{
"question": "우리말과 뜻이 같은 영어 문장을 고르세요.\n\n"침실에는 침대가 두 개 있습니다."",
"options": [
"There is a bed in the bedroom.",
"There are two beds in the bedroom.",
"There are two beds in the bathroom.",
"There are two sofas in the bedroom."
],
"difficulty": "hard",
"reward": 50,
"time": 10,
"answerIndex": 1
},
{
"question": "우리말과 뜻이 같은 영어 문장을 고르세요.\n\n"정말 멋진 집이야!"",
"options": [
"How a nice house!",
"What nice house!",
"What a nice house!",
"So a nice house!"
],
"difficulty": "hard",
"reward": 50,
"time": 10,
"answerIndex": 2
},
{
"question": "다음 낱말을 알맞게 배열한 문장을 고르세요.\n\nis / This / bathroom / the / .",
"options": [
"This the bathroom is.",
"This bathroom is the.",
"This is the bathroom.",
"Bathroom is this the."
],
"difficulty": "medium",
"reward": 50,
"time": 10,
"answerIndex": 2
},
{
"question": "다음 낱말을 알맞게 배열한 문장을 고르세요.\n\nliving room / is / the / This / .",
"options": [
"This is the living room.",
"This the living room is.",
"Living room this is the.",
"The living room is this."
],
"difficulty": "medium",
"reward": 50,
"time": 10,
"answerIndex": 0
},
{
"question": "다음 낱말을 알맞게 배열한 문장을 고르세요.\n\nThere / sofa / in / a / is / the living room / .",
"options": [
"There is a sofa in the living room.",
"There a sofa is in the living room.",
"A sofa there is in the living room.",
"There is in the living room a sofa."
],
"difficulty": "hard",
"reward": 50,
"time": 10,
"answerIndex": 0
},
{
"question": "다음 낱말을 알맞게 배열한 문장을 고르세요.\n\nThere / two / in / beds / bedroom / are / the / .",
"options": [
"There are two beds the in bedroom.",
"There in the bedroom are two beds.",
"There are two beds in the bedroom.",
"Two beds there are bedroom in the."
],
"difficulty": "hard",
"reward": 50,
"time": 10,
"answerIndex": 2
},
{
"question": "다음 낱말을 알맞게 배열한 문장을 고르세요.\n\nnice / house / a / What / !",
"options": [
"What a nice house!",
"A house what nice!",
"Nice what a house!",
"What house a nice!"
],
"difficulty": "hard",
"reward": 50,
"time": 10,
"answerIndex": 0
},
{
"question": "짧은 글을 읽고, 알맞은 장소를 고르세요.\n\nMom: This is the kitchen.\nThere is a stove and a sink.",
"options": [
"침실",
"부엌",
"거실",
"욕실"
],
"difficulty": "easy",
"reward": 50,
"time": 10,
"answerIndex": 1
},
{
"question": "짧은 글을 읽고, 침실에 있는 물건이 아닌 것을 고르세요.\n\nDad: This is the bedroom.\nThere is a bed and a desk.",
"options": [
"bed",
"desk",
"sofa",
"bed and desk"
],
"difficulty": "medium",
"reward": 50,
"time": 10,
"answerIndex": 2
},
{
"question": "짧은 글을 읽고, 질문에 알맞은 답을 고르세요.\n\nThis is my house.\nThis is the living room.\nThere is a sofa in the living room.\n\n질문: 소파는 어디에 있나요?",
"options": [
"in the bedroom",
"in the bathroom",
"in the living room",
"in the kitchen"
],
"difficulty": "medium",
"reward": 50,
"time": 10,
"answerIndex": 2
},
{
"question": "짧은 글을 읽고, 질문에 알맞은 답을 고르세요.\n\nThis is the bathroom.\nThere is a sink and a toilet.\n\n질문: 욕실에 없는 것은 무엇인가요?",
"options": [
"sink",
"toilet",
"bed",
"toilet and sink"
],
"difficulty": "medium",
"reward": 50,
"time": 10,
"answerIndex": 2
},
{
"question": "다음 안내문을 읽고, 어떤 방에 대한 안내인지 고르세요.\n\nWelcome to our room!\nThere are many desks and a big locker.\nThis is our ______.",
"options": [
"bedroom",
"bathroom",
"classroom",
"kitchen"
],
"difficulty": "medium",
"reward": 50,
"time": 10,
"answerIndex": 2
}
]